chainlink_tools/__init__.py
chainlink_tools/__version__.py
chainlink_tools/api.py
chainlink_tools/constants.py
chainlink_tools/scripts.py
chainlink_tools/utils.py
chainlink_tools/bootstrap_jobs/ethbool.json
chainlink_tools/bootstrap_jobs/ethbytes32get.json
chainlink_tools/bootstrap_jobs/ethbytes32post.json
chainlink_tools/bootstrap_jobs/ethint256.json
chainlink_tools/bootstrap_jobs/ethuint256.json
chainlink_tools-0.1.0.data/scripts/chainlink-tools
tests/__init__.py
tests/test_parser.py
tests/test_scripts.py
chainlink_tools-0.1.0.dist-info/LICENSE
chainlink_tools-0.1.0.dist-info/METADATA
chainlink_tools-0.1.0.dist-info/WHEEL
chainlink_tools-0.1.0.dist-info/top_level.txt
chainlink_tools-0.1.0.dist-info/RECORD
