Metadata-Version: 2.1
Name: chainlink-tools
Version: 0.1.0
Summary: Utilities for operating a chainlink node.
Home-page: UNKNOWN
Author: dursk
License: MIT
Project-URL: Source, https://github.com/dursk/chainlink-tools
Keywords: chainlink oracle smart contract
Platform: UNKNOWN
Requires-Dist: requests (==2.22.0)
